{
    "status": "ok",
    "totalResults": 17,
    "articles": [
        {
            "source": {
                "id": "bbc-news",
                "name": "BBC News"
            },
            "author": null,
            "title": "Transfer rumours: Coutinho, Young, Ozil, Doucoure, Robinson",
            "description": "Premier League clubs want cut-price Philippe Coutinho, Bayern Munich president targets Manchester City man, plus more.",
            "url": "https://www.bbc.co.uk/sport/football/51449181",
            "urlToImage": "https://ichef.bbci.co.uk/onesport/cps/624/cpsprodpb/1792A/production/_110845569_coutinho_getty.jpg",
            "publishedAt": "2020-02-10T23:55:40Z",
            "content": "Brazil midfielder Philippe Coutinho, 27, has been told he can leave Barcelona for a cut-price \u00a377m this summer, with Manchester United, Chelsea, Manchester City, Tottenham and former club Liverpool all interested. (Express)\r\nChelsea are winning the race for H\u2026 [+1750 chars]"
        },
        {
            "source": {
                "id": "bbc-news",
                "name": "BBC News"
            },
            "author": null,
            "title": "Coronavirus: China's Xi visits hospital in rare appearance",
            "description": "In a rare public appearance, China's President Xi Jinping has visited health staff in Beijing treating patients infected with the coronavirus. We also hear about how transmissible the virus may become outside of China. Also in the programme: The US charges fo\u2026",
            "url": "https://www.bbc.co.uk/programmes/w172wq55yq239xx",
            "urlToImage": "https://ichef.bbci.co.uk/images/ic/1200x675/p082xshc.jpg",
            "publishedAt": "2020-02-10T22:08:00Z",
            "content": "In a rare public appearance, China's President Xi Jinping has visited health staff in Beijing treating patients infected with the coronavirus. We also hear about how transmissible the virus may become outside of China. \r\nAlso in the programme: The US charges \u2026 [+253 chars]"
        },
        {
            "source": {
                "id": "bbc-news",
                "name": "BBC News"
            },
            "author": "https://www.facebook.com/bbcnews",
            "title": "Coronavirus: China's Xi visits hospital in rare appearance amid health crisis",
            "description": "The leader's visit to a hospital comes as the death toll from the coronavirus surges to more than 900.",
            "url": "https://www.bbc.co.uk/news/world-asia-china-51448571",
            "urlToImage": "https://ichef.bbci.co.uk/news/1024/branded_news/1236C/production/_110840647_059863206-1.jpg",
            "publishedAt": "2020-02-10T16:50:17Z",
            "content": "Image copyrightEPAImage caption\r\n China's president has kept a low profile since the outbreak began\r\nChina's President Xi Jinping has visited health staff in Beijing treating patients infected with the new coronavirus, in a rare public appearance amid the out\u2026 [+5411 chars]"
        },
        {
            "source": {
                "id": "bbc-news",
                "name": "BBC News"
            },
            "author": "https://www.facebook.com/bbcnews",
            "title": "Coronavirus super-spreaders: Why are they important?",
            "description": "Some people pass on their infection to large numbers of people - is it happening with coronavirus?",
            "url": "https://www.bbc.co.uk/news/health-51447143",
            "urlToImage": "https://ichef.bbci.co.uk/news/1024/branded_news/87E9/production/_110839743_crowd.jpg",
            "publishedAt": "2020-02-10T16:43:35Z",
            "content": "Image copyrightGetty Images\r\nSuper-spreading, where individual patients pass on an infection to large numbers of people, is a feature of nearly every outbreak. \r\nIt is not their fault but can have a significant impact on how diseases spread.\r\nThere are report\u2026 [+4041 chars]"
        },
        {
            "source": {
                "id": "bbc-news",
                "name": "BBC News"
            },
            "author": null,
            "title": "Germany's 'successor' to Merkel quits",
            "description": "The decision comes as questions were raised about her ability to command authority in the party, after CDU delegates in eastern Germany defied the party headquarter\u2019s ban on cooperating with the far right Alternative f\u00fcr Deutschland (AfD). China's president X\u2026",
            "url": "https://www.bbc.co.uk/programmes/p082wsxz",
            "urlToImage": "https://ichef.bbci.co.uk/images/ic/1200x675/p07zqpb8.jpg",
            "publishedAt": "2020-02-10T15:33:00Z",
            "content": "The decision comes as questions were raised about her ability to command authority in the party, after CDU delegates in eastern Germany defied the party headquarters ban on cooperating with the far right Alternative f\u00fcr Deutschland (AfD). China's president Xi\u2026 [+169 chars]"
        },
        {
            "source": {
                "id": "bbc-news",
                "name": "BBC News"
            },
            "author": null,
            "title": "China goes back to work amid Coronavirus fears",
            "description": "Employees returning from an extended holiday are facing new measures to contain the virus. Meanwhile the Hong Kong Arts Festival is cancelled. Also in the programme:What makes a \"super-spreader\"? And Sinn Fein makes history in Ireland's elections. (Picture:Co\u2026",
            "url": "https://www.bbc.co.uk/programmes/w172wq55yq22gq0",
            "urlToImage": "https://ichef.bbci.co.uk/images/ic/1200x675/p082wfbv.jpg",
            "publishedAt": "2020-02-10T15:24:00Z",
            "content": "Employees returning from an extended holiday are facing new measures to contain the virus. Meanwhile the Hong Kong Arts Festival is cancelled.\r\nAlso in the programme:What makes a \"super-spreader\"? And Sinn Fein makes history in Ireland's elections.\r\n(Picture:\u2026 [+62 chars]"
        },
        {
            "source": {
                "id": "bbc-news",
                "name": "BBC News"
            },
            "author": "https://www.facebook.com/bbcnews",
            "title": "Brighton GP practice closes due to coronavirus",
            "description": "The NHS took action after a staff member at the County Oak medical centre tested positive for the virus.",
            "url": "https://www.bbc.co.uk/news/uk-51447761",
            "urlToImage": "https://ichef.bbci.co.uk/news/1024/branded_news/5643/production/_110838022_84230294_10158250881778648_4304106904801509376_o.jpg",
            "publishedAt": "2020-02-10T13:34:55Z",
            "content": "A GP practice in Brighton has been temporarily closed after a staff member tested positive for the coronavirus.\r\nPatients at the city's County Oak medical centre have been advised to contact the NHS 111 phone service if they have concerns.\r\nEight people in th\u2026 [+200 chars]"
        },
        {
            "source": {
                "id": "bbc-news",
                "name": "BBC News"
            },
            "author": null,
            "title": "Lewis Hamilton and Mercedes the 'obvious pairing going forward', says Toto Wolff",
            "description": "Mercedes Formula 1 boss Toto Wolff says that Lewis Hamilton staying with the team beyond the end of this season is \"the obvious pairing\".",
            "url": "https://www.bbc.co.uk/sport/formula1/51441666",
            "urlToImage": "https://ichef.bbci.co.uk/onesport/cps/624/cpsprodpb/2CD1/production/_110837411_wolff_getty.jpg",
            "publishedAt": "2020-02-10T12:39:41Z",
            "content": "Hamilton, 35, has been racing in F1 since 2007\r\nMercedes Formula 1 boss Toto Wolff says that Lewis Hamilton staying with the team beyond the end of this season is \"the obvious pairing\".\r\nThe six-time champion's contract runs out at the end of 2020 and he has \u2026 [+5040 chars]"
        },
        {
            "source": {
                "id": "bbc-news",
                "name": "BBC News"
            },
            "author": null,
            "title": "Dele Alli: Tottenham midfielder apologises for coronavirus 'joke'",
            "description": "Tottenham's Dele Alli apologises for a social media post in which he joked about the coronavirus outbreak, saying \"I let myself down and the club\".",
            "url": "https://www.bbc.co.uk/sport/football/51441898",
            "urlToImage": "https://ichef.bbci.co.uk/onesport/cps/624/cpsprodpb/172E9/production/_110835949_gettyimages-1198921174.jpg",
            "publishedAt": "2020-02-10T10:14:22Z",
            "content": "Dele Alli's Tottenham team are back in Premier League action against Aston Villa on Sunday\r\nTottenham Hotspur midfielder Dele Alli has apologised for a post on social media about coronavirus, saying \"I let myself down and the club\".\r\nAlli, 23, put a video on \u2026 [+858 chars]"
        },
        {
            "source": {
                "id": "bbc-news",
                "name": "BBC News"
            },
            "author": null,
            "title": "Coronavirus: Women's World Championship and LPGA Thailand cancelled because of outbreak",
            "description": "Golf's Women's World Championship and the LPGA Thailand event have both been cancelled due to coronavirus.",
            "url": "https://www.bbc.co.uk/sport/golf/51441889",
            "urlToImage": "https://ichef.bbci.co.uk/onesport/cps/624/cpsprodpb/44EB/production/_110834671_gettyimages-1171383733.jpg",
            "publishedAt": "2020-02-10T08:18:58Z",
            "content": "South Korea's Park Sung-hyun won the Women's World Championship in 2019\r\nGolf's Women's World Championship in Singapore and the LPGA Thailand event have both been cancelled because of ongoing concerns about coronavirus.\r\nThe LPGA said because of advice concer\u2026 [+1290 chars]"
        },
        {
            "source": {
                "id": "bbc-news",
                "name": "BBC News"
            },
            "author": "https://www.facebook.com/bbcnews",
            "title": "Coronavirus 'imminent threat' to public health",
            "description": "UK government declares coronavirus a \"serious and imminent threat\" to public health.",
            "url": "https://www.bbc.co.uk/news/uk-51442314",
            "urlToImage": "https://ichef.bbci.co.uk/news/1024/branded_news/7A23/production/_97176213_breaking_news_bigger.png",
            "publishedAt": "2020-02-10T07:31:42Z",
            "content": "The UK government has declared coronavirus a \"serious and imminent threat\" to public health.\r\nHealth Secretary Matt Hancock has announced measures \"to ensure the public are protected\" from the transmission of the virus.\r\nThis breaking news story is being upda\u2026 [+95 chars]"
        },
        {
            "source": {
                "id": "bbc-news",
                "name": "BBC News"
            },
            "author": "https://www.facebook.com/bbcnews",
            "title": "Coronavirus labs to begin testing in Scotland",
            "description": "Two new testing facilities are created in Glasgow and Edinburgh to carry out coronavirus tests.",
            "url": "https://www.bbc.co.uk/news/uk-scotland-51436102",
            "urlToImage": "https://ichef.bbci.co.uk/news/1024/branded_news/C852/production/_110828215_gettyimages-1198900287.jpg",
            "publishedAt": "2020-02-10T06:40:54Z",
            "content": "Image copyrightGetty Images\r\nTwo new testing facilities for the coronavirus have been created in Scotland. \r\nUntil now, all samples taken from people suspected of having the virus in Scotland had been sent to England.\r\nScotland's chief medical officer said la\u2026 [+1487 chars]"
        },
        {
            "source": {
                "id": "bbc-news",
                "name": "BBC News"
            },
            "author": "https://www.facebook.com/bbcnews",
            "title": "News Daily: Storm Ciara, Oscars 2020 and coronavirus latest",
            "description": "Your morning briefing for Monday 10 February 2020.",
            "url": "https://www.bbc.co.uk/news/uk-51422460",
            "urlToImage": "https://ichef.bbci.co.uk/news/1024/branded_news/B132/production/_110826354_hi059818489.jpg",
            "publishedAt": "2020-02-10T06:30:56Z",
            "content": "If you want to get this briefing by email, sign up here\r\nStorm Ciara aftermath\r\nImage copyrightSouth Shore Fire Station\r\nStorm Ciara caused damage and disruption across a swathe of the UK on Sunday. Gusts of wind reached more than 90mph and heavy rain brought\u2026 [+5698 chars]"
        },
        {
            "source": {
                "id": "bbc-news",
                "name": "BBC News"
            },
            "author": "https://www.facebook.com/bbcnews",
            "title": "Coronavirus: Much of 'the world's factory' still shut",
            "description": "Major Apple supplier Foxconn and global car makers among the big manufacturers that have not reopened.",
            "url": "https://www.bbc.co.uk/news/business-51439400",
            "urlToImage": "https://ichef.bbci.co.uk/news/1024/branded_news/12E79/production/_110833477_gettyimages-1199766629.jpg",
            "publishedAt": "2020-02-10T05:51:10Z",
            "content": "Image copyrightGetty ImagesImage caption\r\n A worker disinfecting machines before workers return from their holidays in China's eastern Jiangsu province.\r\nA large number of China's factories remain closed today even as millions of people return to work after t\u2026 [+2405 chars]"
        },
        {
            "source": {
                "id": "bbc-news",
                "name": "BBC News"
            },
            "author": "https://www.facebook.com/bbcnews",
            "title": "Coronavirus claims 97 lives in one day - but number of infections stabilises",
            "description": "Some 908 people have now died in China - but the number of new infections has stabilised.",
            "url": "https://www.bbc.co.uk/news/world-asia-china-51439450",
            "urlToImage": "https://ichef.bbci.co.uk/news/1024/branded_news/113DF/production/_110832607_34560eec-061d-487a-8992-a885397c0893.jpg",
            "publishedAt": "2020-02-10T02:25:41Z",
            "content": "Image copyrightReutersImage caption\r\n Despite the death toll, an increasing number of patients are recovering\r\nThe number of people killed by the new coronavirus rose by 97 on Sunday, the highest number of casualties in a day. \r\nThe total number of deaths in \u2026 [+1723 chars]"
        },
        {
            "source": {
                "id": "bbc-news",
                "name": "BBC News"
            },
            "author": "https://www.facebook.com/bbcnews",
            "title": "Newspaper headlines: 'Storm of the century' and virus 'super-spreader'",
            "description": "The paper's reflect on Storm Ciara, and a Briton is thought to have infected seven with coronavirus.",
            "url": "https://www.bbc.co.uk/news/blogs-the-papers-51438815",
            "urlToImage": "https://ichef.bbci.co.uk/news/1024/branded_news/F55D/production/_110831826_metro.jpg",
            "publishedAt": "2020-02-10T00:31:52Z",
            "content": null
        },
        {
            "source": {
                "id": "bbc-news",
                "name": "BBC News"
            },
            "author": "https://www.facebook.com/bbcnews",
            "title": "Scottish salmon producers warn of 'huge' Brexit burden",
            "description": "The industry says the UK government has told it to prepare for trade barriers with the European Union.",
            "url": "https://www.bbc.co.uk/news/uk-scotland-scotland-business-51437666",
            "urlToImage": "https://ichef.bbci.co.uk/news/1024/branded_news/135D1/production/_110831397_salmonfarm.jpg",
            "publishedAt": "2020-02-10T00:00:15Z",
            "content": "Image copyrightGetty Images\r\nSalmon farmers face \"huge unnecessary burdens\" and a loss of market share under UK government plans for Brexit.\r\nThe chief executive of the Scottish Salmon Producers Organisation (SSPO) said firms were being told to prepare for tr\u2026 [+3529 chars]"
        }
    ]
}