{
    "status": "ok",
    "totalResults": 38,
    "articles": [
        {
            "source": {
                "id": "fox-news",
                "name": "Fox News"
            },
            "author": "Bradford Betz",
            "title": "How is coronavirus transmitted?",
            "description": "Since it was first reported in China last month, the deadly coronavirus has spread to more than a dozen countries, with more than 7,800 cases reported and 170 deaths.",
            "url": "https://www.foxnews.com/health/how-is-coronavirus-transmitted",
            "urlToImage": "https://static.foxnews.com/foxnews.com/content/uploads/2020/01/AP20030519469863.jpg",
            "publishedAt": "2020-01-30T23:49:07Z",
            "content": "Since it was first reported in China last month, the deadly coronavirus has spread to more than a dozen countries, with more than 7,800 cases reported and 170 deaths.\r\nThe World Health Organization on Thursday declared the outbreak a global emergency after th\u2026 [+2443 chars]"
        },
        {
            "source": {
                "id": "fox-news",
                "name": "Fox News"
            },
            "author": null,
            "title": "Officials confirm first US human-to-human transmission of coronavirus",
            "description": "The coronavirus patient is the husband of a Chicago traveler who became ill shortly after returning from Wuhan, China; Jonathan Serrie reports.",
            "url": "http://video.foxnews.com/v/6128463068001/",
            "urlToImage": "https://cf-images.us-east-1.prod.boltdns.net/v1/static/694940094001/81f7e4f2-11cf-4d69-9099-6443b855c2a5/93a7e4dd-aa72-4de7-a475-c4feabc001e7/1280x720/match/image.jpg",
            "publishedAt": "2020-01-30T23:48:25Z",
            "content": null
        },
        {
            "source": {
                "id": "fox-news",
                "name": "Fox News"
            },
            "author": "Gerren Keith Gaynor",
            "title": "American Airlines sued over coronavirus by pilot union seeking to cancel US-China flights",
            "description": "The Allied Pilots Association seeks temporary restraining order amid deadly virus outbreak.",
            "url": "https://www.foxnews.com/travel/coronavirus-american-airlines-lawsuit-pilot",
            "urlToImage": "https://static.foxnews.com/foxnews.com/content/uploads/2020/01/American-Airlines-Plane-iStock.jpg",
            "publishedAt": "2020-01-30T22:56:46Z",
            "content": "American Airlines has been hit with a lawsuit by a pilot union demanding that the airline immediately halt flights between the U.S. and China amid the coronavirus outbreak. \r\nThe lawsuit, filed by the Allied Pilots Association in Dallas County on Thursday, is\u2026 [+3962 chars]"
        },
        {
            "source": {
                "id": "fox-news",
                "name": "Fox News"
            },
            "author": "Matt London",
            "title": "'Many of you parents have failed': David Webb on report kids suffer anxiety related to phones",
            "description": "Fox News contributor David Webb has a tough message for some of the parents of children, who suffer from unhealthy relationships with technology, \"you... have failed.\"",
            "url": "https://www.foxnews.com/media/technology-students-health-schools-david-webb",
            "urlToImage": "https://static.foxnews.com/foxnews.com/content/uploads/2020/01/Webb-KidsPhone.jpg",
            "publishedAt": "2020-01-30T22:53:31Z",
            "content": "Fox News contributor David Webb has a tough message for some of the parents of children\u00a0who suffer from\u00a0unhealthy relationships with technology:\u00a0\"You ... have failed.\"\r\nOn Fox Nation's\"Reality Check,\" Webb reacted to a Wall Street Journal report that efforts \u2026 [+2795 chars]"
        },
        {
            "source": {
                "id": "fox-news",
                "name": "Fox News"
            },
            "author": "Gerren Keith Gaynor",
            "title": "Chinese dog owners are buying coronavirus masks for their pooches",
            "description": "Dog owners in China are taking no chances when it comes to the health of their pooches.",
            "url": "https://www.foxnews.com/lifestyle/dog-masks-coronavirus",
            "urlToImage": "https://static.foxnews.com/foxnews.com/content/uploads/2020/01/Dog-Mask-Split.jpg",
            "publishedAt": "2020-01-30T22:27:48Z",
            "content": "Dog owners in China are taking no chances when it comes to the health of their pooches. \r\nSales of face masks for dogs, bought with the hope they will\u00a0protect canines from the coronavirus outbreak, have skyrocketed since the deadly disease was first reported \u2026 [+2541 chars]"
        },
        {
            "source": {
                "id": "fox-news",
                "name": "Fox News"
            },
            "author": "Christopher Carbone",
            "title": "Antarctica\u2019s \u2018doomsday glacier\u2019 reveals alarming new trait to scientists",
            "description": "Scientists have detected unusually warm water underneath Antarctica's 'Doomsday Glacier.'",
            "url": "https://www.foxnews.com/science/antarctica-doomsday-glacier-alarming-new-trait",
            "urlToImage": "https://static.foxnews.com/foxnews.com/content/uploads/2018/09/thwaites-glacier.jpg",
            "publishedAt": "2020-01-30T21:53:13Z",
            "content": "Scientists have detected unusually warm water underneath Antarctica's \"doomsday glacier.\"\r\nThe team from Georgia Tech was able capture new images and first-of-its-kind data from deep beneath Thwaites Glacier -- which earned its \"doomsday\"\u00a0nickname because it \u2026 [+2322 chars]"
        },
        {
            "source": {
                "id": "fox-news",
                "name": "Fox News"
            },
            "author": "James Rogers",
            "title": "Coronavirus: Satellite images show construction of Wuhan hospitals",
            "description": "Satellite images show the hospitals being built to deal with the deadly coronavirus outbreak in the Chinese city of Wuhan.",
            "url": "https://www.foxnews.com/science/coronavirus-satellite-images-wuhan-hospitals-construction",
            "urlToImage": "https://static.foxnews.com/foxnews.com/content/uploads/2020/01/WuhanMaxar3.jpg",
            "publishedAt": "2020-01-30T21:48:51Z",
            "content": "Satellite images show the hospitals being built to deal with the deadly coronavirus outbreak in the Chinese city of Wuhan.\r\nThe images were captured on Jan. 29, 2020, by satellite technology operated by Maxar Technologies. Images captured by the Copernicus Se\u2026 [+1185 chars]"
        },
        {
            "source": {
                "id": "fox-news",
                "name": "Fox News"
            },
            "author": "Matt London",
            "title": "Coronavirus outbreak in U.S. may depend on this: 'We just don't know yet' says infectious disease doc",
            "description": "A top infectious disease doctor warned that the likelihood of preventing a U.S. outbreak of the coronavirus depends\u00a0on whether the virus\u00a0is transmitted by people, who are not exhibiting symptoms.\u00a0 And that information, he warned, is something that world healt\u2026",
            "url": "https://www.foxnews.com/media/coronavirus-u-s-outbreak-contain-emergency",
            "urlToImage": "https://static.foxnews.com/foxnews.com/content/uploads/2020/01/China-Outbreak-US-AP.jpg",
            "publishedAt": "2020-01-30T21:16:56Z",
            "content": "A top infectious disease doctor warned that the likelihood of preventing a U.S. outbreak of the coronavirus depends\u00a0on whether the virus\u00a0is transmitted by people\u00a0who are not exhibiting symptoms.\u00a0And that information, he warned, is something that world health \u2026 [+3485 chars]"
        },
        {
            "source": {
                "id": "fox-news",
                "name": "Fox News"
            },
            "author": "Bradford Betz",
            "title": "How did the coronavirus outbreak start?",
            "description": "The deadly coronavirus which broke out in China has gripped the international community by fear, as cases continue to mount, and world leaders struggle to contain the epidemic.",
            "url": "https://www.foxnews.com/health/how-did-the-coronavirus-outbreak-start",
            "urlToImage": "https://static.foxnews.com/foxnews.com/content/uploads/2020/01/AP20030595268074-1.jpg",
            "publishedAt": "2020-01-30T20:42:36Z",
            "content": "The deadly coronavirus which broke out in China late last month has gripped the international community by fear, as cases continue to mount, and world leaders struggle to contain the epidemic. \r\nAs of Thursday, there have 7,736 confirmed cases in China, with \u2026 [+2563 chars]"
        },
        {
            "source": {
                "id": "fox-news",
                "name": "Fox News"
            },
            "author": "Alexandria Hein",
            "title": "Coronavirus evacuee quarantined after arriving in California, health department says",
            "description": "The passenger, who arrived on a flight from Wuhan with nearly 200 other Americans on Wednesday, had attempted to leave the air base, officials said.",
            "url": "https://www.foxnews.com/health/wuhan-coronavirus-evacuee-quarantined-in-california-health-department",
            "urlToImage": "https://cf-images.us-east-1.prod.boltdns.net/v1/static/694940094001/85eca00c-b21a-4af2-a858-efa783cee55c/ade642ee-eb33-4b4d-b3a5-492ea02f0af4/1280x720/match/image.jpg",
            "publishedAt": "2020-01-30T20:11:44Z",
            "content": "Health officials have issued a quarantine order for one of the passengers who arrived in California yesterday on a flight from Wuhan. The passenger, who is one of nearly 200 Americans evacuated from the coronavirus epicenter, had attempted to leave the March \u2026 [+2664 chars]"
        },
        {
            "source": {
                "id": "fox-news",
                "name": "Fox News"
            },
            "author": "Vandana Rambaran",
            "title": "World Health Organization declares coronavirus outbreak a global health emergency",
            "description": "The World Health Organization on Thursday declared the new coronavirus outbreak a global emergency amid the recent jump in the number of infected patients.",
            "url": "https://www.foxnews.com/health/world-health-organization-declares-coronavirus-outbreak-a-global-health-emergency",
            "urlToImage": "https://static.foxnews.com/static/orion/styles/img/fox-news/og/og-fox-news.png",
            "publishedAt": "2020-01-30T19:58:22Z",
            "content": "The World Health Organization on Thursday declared the new coronavirus outbreak a global emergency amid the recent jump in the number of infected patients.\r\n\"The main reason is not what is happening in China but what is happening in other countries,\"\u00a0WHO chie\u2026 [+1383 chars]"
        },
        {
            "source": {
                "id": "fox-news",
                "name": "Fox News"
            },
            "author": "Alexandria Hein",
            "title": "How China is building a coronavirus hospital in a week",
            "description": "China announced plans for a 1,000-bed hospital in Wuhan to combat the coronavirus outbreak.",
            "url": "https://www.foxnews.com/health/how-china-building-coronavirus-hospital-in-a-week",
            "urlToImage": "https://static.foxnews.com/foxnews.com/content/uploads/2020/01/china_hospital_ap.jpg",
            "publishedAt": "2020-01-30T19:54:17Z",
            "content": "In a bid to address the soaring number of coronavirus cases in Wuhan and nearby cities, Chinese officials ordered the construction of a 1,000-bed hospital that they aim\u00a0to have completed by Feb.\u00a03. The plans, officials said, would follow a similar model to th\u2026 [+2795 chars]"
        },
        {
            "source": {
                "id": "fox-news",
                "name": "Fox News"
            },
            "author": "Talia Kaplan",
            "title": "HHS Secretary Azar on coronavirus: 'We will take all... measures necessary to protect the American public'",
            "description": "Health and Human Services Secretary Alex Azar, who has been appointed by President Trump to lead a coronavirus task force, appeared on \u201cAmerica\u2019s Newsroom\u201d on Thursday to discuss the steps the White House is taking to prevent the further spread of the virus i\u2026",
            "url": "https://www.foxnews.com/media/hhs-secretary-azar-leading-coronavirus-task-force-to-address-us-response-to-outbreak",
            "urlToImage": "https://static.foxnews.com/foxnews.com/content/uploads/2020/01/task-force.jpg",
            "publishedAt": "2020-01-30T18:36:09Z",
            "content": "Health and Human Services Secretary Alex Azar, who has been appointed by President Trump to lead a\u00a0coronavirus task force, appeared on \u201cAmerica\u2019s Newsroom\u201d on Thursday to discuss the steps the White House is taking to prevent the further spread of the virus i\u2026 [+4178 chars]"
        },
        {
            "source": {
                "id": "fox-news",
                "name": "Fox News"
            },
            "author": "Alexandria Hein",
            "title": "Person-to-person transmission of coronavirus reported in US, CDC says",
            "description": "The case involves the spouse of an Illinois woman who had contracted the virus after traveling to China.",
            "url": "https://www.foxnews.com/health/person-to-person-transmission-coronavirus-reported-in-us-cdc",
            "urlToImage": "https://cf-images.us-east-1.prod.boltdns.net/v1/static/694940094001/c33cf7d6-0b46-4809-9f33-a82c35e6029f/9495e15c-12dd-4464-8ae3-ba035a0839e0/1280x720/match/image.jpg",
            "publishedAt": "2020-01-30T17:49:17Z",
            "content": "The Centers for Disease Control and Prevention (CDC) has reported the first case of person-to-person transmission of coronavirus in the U.S. In a telebriefing on Thursday, Dr. Robert Redfield, the CDC director, said the health agency had expected to identify \u2026 [+718 chars]"
        },
        {
            "source": {
                "id": "fox-news",
                "name": "Fox News"
            },
            "author": "Janine Puhak",
            "title": "Airlines remove hot food, blankets, magazines and more amid coronavirus outbreak",
            "description": "Frequent flyers will have to do without some favorite amenities.",
            "url": "https://www.foxnews.com/travel/airlines-coronavirus-outbreak-amenities-remove",
            "urlToImage": "https://static.foxnews.com/foxnews.com/content/uploads/2020/01/GettyImages-892164296.jpg",
            "publishedAt": "2020-01-30T15:50:13Z",
            "content": "Air travelers\u00a0will have to do without amenities like blankets, pillows and hot meals on some flights to and from China for the foreseeable future, as several airlines have removed the niceties over coronavirus contagion concerns.\r\nChina Airlines, Mandarin Air\u2026 [+2826 chars]"
        },
        {
            "source": {
                "id": "fox-news",
                "name": "Fox News"
            },
            "author": "Alexandra Deabler",
            "title": "United Airlines suspending more flights amid coronavirus outbreak",
            "description": "United Airlines is implementing a second phase of temporary flight suspensions to China.",
            "url": "https://www.foxnews.com/travel/united-airlines-suspending-more-flights-amid-coronavirus-outbreak",
            "urlToImage": "https://static.foxnews.com/foxnews.com/content/uploads/2020/01/UNitedAirlinesiStok.png",
            "publishedAt": "2020-01-30T15:42:09Z",
            "content": "United Airlines is implementing a second phase of temporary flight suspensions to China amid the coronavirus outbreak, the airline shared with Fox News Thursday.\r\n7,000 PEOPLE HELD ON CRUISE SHIP AFTER PASSENGER DEVELOPS SUSPECTED CORONAVIRUS SYMPTOMS\r\n\u201cAs th\u2026 [+1917 chars]"
        },
        {
            "source": {
                "id": "fox-news",
                "name": "Fox News"
            },
            "author": "Peter Hotez",
            "title": "Dr. Peter Hotez: What coronavirus means for the U.S., China and the world",
            "description": "Coronavirus is going to inflict serious public health and economic damage in China, and there is a risk that it could gain a foothold elsewhere.",
            "url": "https://www.foxnews.com/opinion/a-tale-of-3-nations-peter-hotez",
            "urlToImage": "https://cf-images.us-east-1.prod.boltdns.net/v1/static/694940094001/002dabdb-ec14-48d6-97a5-fd5f74b897c4/461f3b6f-591f-4ba1-a642-5deee60f405e/1280x720/match/image.jpg",
            "publishedAt": "2020-01-30T15:23:44Z",
            "content": "The number of cases of the Novel Coronavirus (nCoV) that emerged in Wuhan in Central China is accelerating rapidly. It presently stands at more than 6,000, with at least 130 deaths. The actual number is far greater if we also consider undiagnosed patients wit\u2026 [+5449 chars]"
        },
        {
            "source": {
                "id": "fox-news",
                "name": "Fox News"
            },
            "author": "Michael Bartiromo",
            "title": "Moviegoers hospitalized after cleaning fluid is accidentally mixed into their drinks",
            "description": "Police told Fox News that the cleaning solution was being stored in a repurposed Pama Pomegranate Liqueur bottle.",
            "url": "https://www.foxnews.com/health/moviegoers-hospitalized-cleaning-fluid-idrinks",
            "urlToImage": "https://static.foxnews.com/foxnews.com/content/uploads/2020/01/HoldMouthIstock.jpg",
            "publishedAt": "2020-01-30T15:23:15Z",
            "content": "A pair of moviegoers in Nebraska were hospitalized earlier this week after they ingested cleaning fluid that had accidentally been mixed into their drinks, police say.\r\nThe two women had gone to see a movie at the Alamo Drafthouse Cinemas location in La Vista\u2026 [+2299 chars]"
        },
        {
            "source": {
                "id": "fox-news",
                "name": "Fox News"
            },
            "author": "Janine Puhak",
            "title": "7,000 people held on cruise ship after passenger develops suspected coronavirus symptoms",
            "description": "A Costa Cruises spokesperson confirmed the situation to Fox News on Thursday.",
            "url": "https://www.foxnews.com/travel/7000-people-held-cruise-ship-coronavirus-passenger-suspected-symptoms-report",
            "urlToImage": "https://static.foxnews.com/foxnews.com/content/uploads/2020/01/AP20030454514886.jpg",
            "publishedAt": "2020-01-30T15:13:47Z",
            "content": "About 6,000 passengers and 1,000 crew aboard Costa Cruises\u2019 Costa Smeralda ship were being held in an Italian port after a passenger from Macau, China, came down with flu-like symptoms on Wednesday night\u00a0amid the ongoing coronavirus outbreak.\r\nA Costa Cruises\u2026 [+3801 chars]"
        },
        {
            "source": {
                "id": "fox-news",
                "name": "Fox News"
            },
            "author": "Associated Press",
            "title": "German nurse suspected of drugging 5 infants with morphine: authorities",
            "description": "A nurse at a German hospital has been arrested on suspicion that she administered morphine to five young babies, who were later found by staff with life-threatening breathing difficulties, officials said Thursday.",
            "url": "https://www.foxnews.com/world/germany-nurse-drugging-infants-morphine-arrested",
            "urlToImage": "https://static.foxnews.com/foxnews.com/content/uploads/2020/01/ulm-clinic-Reuters.jpg",
            "publishedAt": "2020-01-30T14:58:09Z",
            "content": "A nurse at a German hospital has been arrested on suspicion that she administered morphine to five young babies, who were later found by staff with life-threatening breathing difficulties, officials said Thursday.\r\nThe five babies at the University Hospital i\u2026 [+1111 chars]"
        },
        {
            "source": {
                "id": "fox-news",
                "name": "Fox News"
            },
            "author": "Alexandria Hein",
            "title": "Coronavirus fears sees taxi driver don hazmat suit, goggles to pick up passenger",
            "description": "The driver allegedly wore a hazmat suit and goggles to pick up his passenger.",
            "url": "https://www.foxnews.com/health/coronavirus-fears-taxi-driver-hazmat-suit-goggles",
            "urlToImage": "https://static.foxnews.com/foxnews.com/content/uploads/2020/01/Hazmat-Cabbie-3-AsiaWire.jpg",
            "publishedAt": "2020-01-30T14:51:10Z",
            "content": "With the number of coronavirus cases in mainland China now surpassing those of the 2002-2003 deadly SARS outbreak, fears of contracting the illness have driven some to extreme safety measures. Such is the case with one unnamed taxi driver in Beijing, who was \u2026 [+2693 chars]"
        },
        {
            "source": {
                "id": "fox-news",
                "name": "Fox News"
            },
            "author": "Madeline Farber",
            "title": "Asian students at ASU say coronavirus case at school has made other students treat them differently",
            "description": "Some Asian students at Arizona State University (ASU) claim they are being treated differently by the rest of the student body following confirmation of the nation\u2019s fifth case of the deadly coronavirus at the school.",
            "url": "https://www.foxnews.com/health/asian-students-asu-coronavirus-treated-differently",
            "urlToImage": "https://cf-images.us-east-1.prod.boltdns.net/v1/static/694940094001/95f6369e-ce4e-4307-9a60-2098ef7656cb/fc311d0b-b150-4e9d-bb61-4786b7295cc9/1280x720/match/image.jpg",
            "publishedAt": "2020-01-30T14:44:32Z",
            "content": "Some Asian students at Arizona State University (ASU) claim they are being treated differently by the rest of the student body following confirmation of the nation\u2019s fifth case of the deadly coronavirus at the school.\r\n\u201cI cough in class and everybody looks at\u2026 [+2744 chars]"
        },
        {
            "source": {
                "id": "fox-news",
                "name": "Fox News"
            },
            "author": "Caleb Parke",
            "title": "Wuhan, China pastor pens letter on how 'the church should face' coronavirus outbreak",
            "description": "A Chinese pastor in the quarantined city where the coronavirus broke out is calling for prayer as he grapples with how his family and the global church should react.",
            "url": "https://www.foxnews.com/faith-values/coronavirus-china-wuhan-christian-pastor",
            "urlToImage": "https://static.foxnews.com/foxnews.com/content/uploads/2020/01/WuhanChina.jpg",
            "publishedAt": "2020-01-30T14:43:49Z",
            "content": "A Chinese pastor in the quarantined city\u00a0where the coronavirus broke out, Wuhan, is calling for prayer as he grapples with how his family and the global church should react.\r\nThe Christian leader, identified as \"A Wuhan Pastor\" by China Source, sent an open l\u2026 [+2465 chars]"
        },
        {
            "source": {
                "id": "fox-news",
                "name": "Fox News"
            },
            "author": "Julia Musto",
            "title": "Dr. Drew Pinsky hits Adam Schiff on homeless crisis in his own district: 'He's asleep at the wheel'",
            "description": "Senate impeachment trial manager Rep. Adam Schiff, D-Calif. is \"asleep at the wheel\" in his own district and ignoring issues that matter like the state's homeless crisis, Dr. Drew. Pinsky said Thursday.",
            "url": "https://www.foxnews.com/media/dr-drew-pinsky-adam-schiff-homeless-crisis-california",
            "urlToImage": "https://static.foxnews.com/foxnews.com/content/uploads/2020/01/drew-schiff-homeless-FOX-AP.jpg",
            "publishedAt": "2020-01-30T14:35:54Z",
            "content": "Senateimpeachment trial manager Rep. Adam Schiff, D-Calif., is \"asleep at the wheel\" when it comes to\u00a0his own district and is ignoring issues that matter, like the state's homeless crisis,\u00a0Dr. Drew. Pinsky said Thursday.\r\nAppearing on \"Fox &amp; Friends\" with\u2026 [+1974 chars]"
        },
        {
            "source": {
                "id": "fox-news",
                "name": "Fox News"
            },
            "author": "Victor Garcia",
            "title": "American describes scene in Wuhan amid coronavirus outbreak: 'Like something out of a sci-fi movie'",
            "description": "What's it like to be stuck in the Chinese city where the deadly coronavirus began? The \"Fox News Rundown\" podcast spoke with Doug Perez, an American living in Wuhan who spoke in detail about what it's like to live in a quarantined city.",
            "url": "https://www.foxnews.com/media/american-in-stuck-in-wuhan-during-the-deadly-coronavirus-outbreak-speaks",
            "urlToImage": "https://static.foxnews.com/foxnews.com/content/uploads/2020/01/AP20022434749667-1-1.jpg",
            "publishedAt": "2020-01-30T11:46:20Z",
            "content": "What's it like to be stuck at ground zero for the deadly coronavirus\u00a0outbreak in China? Doug Perez, an American living in the quarantined city of Wuhan, described his experiences on Thursday's edition of the \"Fox News Rundown\" podcast.\r\n\"Whenever we leave [th\u2026 [+2609 chars]"
        },
        {
            "source": {
                "id": "fox-news",
                "name": "Fox News"
            },
            "author": "Victor Garcia",
            "title": "American describes scene in Wuhan amid coronavirus outbreak: 'Like something out of a sci-fi movie'",
            "description": "What's it like to be stuck in the Chinese city where the deadly coronavirus began? The \"Fox News Rundown\" podcast spoke with Doug Perez, an American living in the quarantined city of Wuhan.",
            "url": "https://www.foxnews.com/health/american-in-stuck-in-wuhan-during-the-deadly-coronavirus-outbreak-speaks",
            "urlToImage": "https://static.foxnews.com/foxnews.com/content/uploads/2020/01/AP20022434749667-1-1.jpg",
            "publishedAt": "2020-01-30T11:46:20Z",
            "content": "What's it like to be stuck in\u00a0ground zero for the deadly coronavirus\u00a0outbreak in China? Doug Perez, an American living in the quarantined city of Wuhan, described his experiences on Thursday's edition of the \"Fox News Rundown\" podcast.\r\nHe said he barely leav\u2026 [+2641 chars]"
        },
        {
            "source": {
                "id": "fox-news",
                "name": "Fox News"
            },
            "author": "David Aaro",
            "title": "Russia closes border with China as coronavirus spreads: reports",
            "description": "Russian Prime Minister Mikhail Mishustin signed an order on Thursday to close the border between Russia and China, according to local reports.",
            "url": "https://www.foxnews.com/world/russia-signs-order-close-border-china",
            "urlToImage": "https://static.foxnews.com/foxnews.com/content/uploads/2020/01/AP20022434749667-1-1.jpg",
            "publishedAt": "2020-01-30T11:03:39Z",
            "content": "Russia has closed its border with China\u00a0over\u00a0coronavirus\u00a0fears, according to local reports.\r\nPrime Minister Mikhail Mishustin signed an order on Thursday to close the border, which he says will be carried out immediately, according to the Moscow Times.\r\n\u201cWe\u2019l\u2026 [+1500 chars]"
        },
        {
            "source": {
                "id": "fox-news",
                "name": "Fox News"
            },
            "author": "David Aaro",
            "title": "Coronavirus death toll increases, here's the latest update on cases",
            "description": "The figures on those impacted by the coronavirus continue to grow weeks after Chinese officials announced the outbreak of a new virus.",
            "url": "https://www.foxnews.com/health/coronavirus-by-the-numbers",
            "urlToImage": "https://static.foxnews.com/foxnews.com/content/uploads/2020/01/AP20029538081493.jpg",
            "publishedAt": "2020-01-30T10:45:56Z",
            "content": "Weeks after China announced the outbreak of the coronavirus, the international community has taken measures to prevent a widespread epidemic.\r\nCountries have begun to limit travel to the infected mainland China and Hubei province -- the epicenter of the virus\u2026 [+2692 chars]"
        },
        {
            "source": {
                "id": "fox-news",
                "name": "Fox News"
            },
            "author": "Jack Durschlag",
            "title": "NJ mayor admits getting drunk at party, removing pants, passing out in employee's bed, report says",
            "description": "The mayor of a New Jersey town admitted he recently got drunk at a party at a township employee\u2019s house, took off his pants and passed out in her bed, according to a report.",
            "url": "https://www.foxnews.com/politics/n-j-mayor-admits-over-drinking-at-party-removing-pants-passing-out-in-employees-bed",
            "urlToImage": "https://static.foxnews.com/foxnews.com/content/uploads/2020/01/mayorroth-cropped-447am.jpg",
            "publishedAt": "2020-01-30T10:10:14Z",
            "content": "The mayor of a New Jersey town admitted he recently got drunk\u00a0at a party at a township employee\u2019s house, took off his pants and passed out in her bed, according to a report.\r\nMayor John Roth said he apologized to the unidentified employee, NorthJersey.com rep\u2026 [+996 chars]"
        },
        {
            "source": {
                "id": "fox-news",
                "name": "Fox News"
            },
            "author": "Fox News",
            "title": "Today on Fox News: Jan. 30, 2020",
            "description": "",
            "url": "https://www.foxnews.com/media/today-on-fox-news-jan-30-2020",
            "urlToImage": "https://static.foxnews.com/foxnews.com/content/uploads/2019/04/fox-news-channel-logo.jpg",
            "publishedAt": "2020-01-30T10:02:41Z",
            "content": "STAY TUNED\r\nOn Fox News:\r\nFox &amp; Friends, 6 a.m. ET: Britain will officially leave the European Union this weekend. Nigel Farage, leader of the Brexit Party, weighs in. Dr. Drew Pinsky shares his plan to solve the homeless and opioid crises. U.S. Sen. Mike\u2026 [+1514 chars]"
        },
        {
            "source": {
                "id": "fox-news",
                "name": "Fox News"
            },
            "author": "William Sanchez",
            "title": "Countdown to the Caucuses: Who will Iowa Choose?",
            "description": "The Iowa Caucuses are quickly approaching. Plus, commentary by Peter Schweizer.",
            "url": "https://radio.foxnews.com/2020/01/30/the-fox-news-rundown-1-30-2020-2/",
            "urlToImage": "https://radio.foxnews.com/wp-content/uploads/2018/04/rundown-featured.png",
            "publishedAt": "2020-01-30T10:00:01Z",
            "content": "The Iowa Caucuses are quickly approaching. The first in the nation state will decide who should take on President Trump as the Democratic nominee this November. Early polling has left it unclear who Iowans will get behind on Caucus night and there are many is\u2026 [+581 chars]"
        },
        {
            "source": {
                "id": "fox-news",
                "name": "Fox News"
            },
            "author": "Fox News",
            "title": "Old videos of Bolton, Schiff raise credibility questions amid Trump impeachment trial",
            "description": "",
            "url": "https://www.foxnews.com/us/old-videos-of-bolton-schiff-raise-credibility-questions-amid-trump-impeachment-trial",
            "urlToImage": "https://static.foxnews.com/foxnews.com/content/uploads/2020/01/Schiff-Bolton-Trump013020.jpg",
            "publishedAt": "2020-01-30T09:34:17Z",
            "content": "Good morning and welcome to Fox News First. Here's what you need to know as you start your day ...\r\n'GAME OVER,' Trump declares, as old Bolton, Schiff videos surface amid Senate impeachment trialA string of newly resurfaced video clips of former national secu\u2026 [+5085 chars]"
        },
        {
            "source": {
                "id": "fox-news",
                "name": "Fox News"
            },
            "author": "David Aaro",
            "title": "World Health Organization may consider coronavirus a public health emergency, death toll hits 170",
            "description": "The World Health Organization (WHO) has called for an Emergency Committee meeting on Thursday on whether the coronavirus constitutes a public health emergency of international concern.",
            "url": "https://www.foxnews.com/health/world-health-organization-consider-coronavirus-public-health-emergency",
            "urlToImage": "https://static.foxnews.com/foxnews.com/content/uploads/2020/01/AP20029467467459-1.jpg",
            "publishedAt": "2020-01-30T08:01:13Z",
            "content": "The World Health Organization (WHO) has\u00a0called for an Emergency Committee meeting on Thursday to determine whether the coronavirus constitutes a public health emergency of international concern.\r\nThe committee will consider issuing a global alarm -- as the de\u2026 [+4328 chars]"
        },
        {
            "source": {
                "id": "fox-news",
                "name": "Fox News"
            },
            "author": "Dom Calicchio",
            "title": "Coronavirus joke gets ESPN\u2019s Richard Jefferson called for a foul on social media",
            "description": "ESPN color commenter Richard Jefferson was known as a pretty good shooter during his time in the NBA. But on Wednesday night, Jefferson\u2019s coronavirus joke about a Detroit Pistons player was a total misfire in the view of many fans on social media.",
            "url": "https://www.foxnews.com/sports/espns-richard-jefferson-draws-fire-for-coronavirus-joke-during-nba-broadcast",
            "urlToImage": "https://static.foxnews.com/foxnews.com/content/uploads/2018/09/062216-NBA-Richard-Jefferson-Clevel-6294d99dee3c5510VgnVCM100000d7c1a8c0____.jpg",
            "publishedAt": "2020-01-30T07:17:50Z",
            "content": "ESPN color commenter Richard Jefferson was known as a pretty good shooter during his time in the NBA.\r\nBut on Wednesday night, Jefferson\u2019s coronavirus joke about a Detroit Pistons player was a total misfire in the view of many fans on social media.\r\nWhile wor\u2026 [+2435 chars]"
        },
        {
            "source": {
                "id": "fox-news",
                "name": "Fox News"
            },
            "author": "Frank Miles",
            "title": "How does coronavirus compare to SARS and MERS outbreaks?",
            "description": "The world is frantically working to contain the coronavirus, which is starting to spread to more people, both inside and outside of China where it originated.",
            "url": "https://www.foxnews.com/health/how-does-coronavirus-compare-to-sars-mers-outbreaks",
            "urlToImage": "https://cf-images.us-east-1.prod.boltdns.net/v1/static/694940094001/31c12eaf-1cd2-41ab-9f8d-a17f9fac255b/53d9d350-3d0f-42f9-9d53-45b18b204075/1280x720/match/image.jpg",
            "publishedAt": "2020-01-30T03:21:35Z",
            "content": "The world is frantically working to contain the\u00a0coronavirus, which is starting to spread to more people\u00a0both inside and outside of\u00a0China,\u00a0where it originated.\r\nThe new virus is from the coronavirus family, which includes those viruses\u00a0that can cause the commo\u2026 [+4069 chars]"
        },
        {
            "source": {
                "id": "fox-news",
                "name": "Fox News"
            },
            "author": "Joseph Wulfsohn",
            "title": "'Contagion' climbs iTunes movie charts as coronavirus outbreak spreads",
            "description": "The outbreak of the deadly coronavirus has caused a recent surge in viewership of the 2011 thriller \"Contagion.\"",
            "url": "https://www.foxnews.com/entertainment/contagion-itunes-movie-charts-coronavirus",
            "urlToImage": "https://static.foxnews.com/foxnews.com/content/uploads/2020/01/Contagion-Coronavirus.jpg",
            "publishedAt": "2020-01-30T02:03:58Z",
            "content": "The outbreak of the deadly coronavirus has caused a recent surge in viewership of the 2011 thriller \"Contagion.\"\r\nAs more cases of coronavirus have emerged in the U.S., The Hollywood Reporter reported the Steven Soderbergh flick in the Top 10\u00a0films on iTunes \u2026 [+1643 chars]"
        },
        {
            "source": {
                "id": "fox-news",
                "name": "Fox News"
            },
            "author": "Bradford Betz",
            "title": "5 cases of coronavirus confirmed in US, risk of spreading remains low, CDC says",
            "description": "The Centers for Disease Control and Prevention (CDC) on Wednesday confirmed only five cases of the deadly coronavirus in the United States but noted that risk to the general American public remains low.",
            "url": "https://www.foxnews.com/health/cases-coronavirus-confirmed-us-risk-spreading-remains-low-cdc",
            "urlToImage": "https://static.foxnews.com/foxnews.com/content/uploads/2020/01/AP20029259567915.jpg",
            "publishedAt": "2020-01-30T00:16:41Z",
            "content": "The Centers for Disease Control and Prevention (CDC) on Wednesday confirmed only five cases of the deadly coronavirus in the United States but noted that risk to the general American public remains low. \r\nThe five were among 165 suspected cases of the coronav\u2026 [+3169 chars]"
        },
        {
            "source": {
                "id": "fox-news",
                "name": "Fox News"
            },
            "author": "Louis Casiano",
            "title": "Coronavirus prompts McDonald's to widen store closures across Chinese province of Hubei",
            "description": "McDonald's has shut down several hundred of its restaurants in China amid concerns the ongoing coronavirus that has claimed the lives of more than 130 people and infected thousands of others globally.",
            "url": "https://www.foxnews.com/food-drink/coronavirus-mcdonalds-store-closures-hubei",
            "urlToImage": "https://static.foxnews.com/foxnews.com/content/uploads/2020/01/AP20026472013598-1.jpg",
            "publishedAt": "2020-01-30T00:05:09Z",
            "content": "McDonald's has shut down several hundred\u00a0of its restaurants in China amid concerns related to\u00a0coronavirus, which\u00a0has claimed the lives of more than 130 people and infected thousands of others globally.\r\nThe closing of its locations in Hubei, the Chinese provi\u2026 [+2010 chars]"
        }
    ]
}