{
    "status": "ok",
    "totalResults": 4,
    "articles": [
        {
            "source": {
                "id": "new-scientist",
                "name": "New Scientist"
            },
            "author": "Debora MacKenzie",
            "title": "How bad is the Covid-19 coronavirus outbreak likely to get?",
            "description": "The death rate of Covid-19, caused by the new coronavirus, may be lower than some estimates suggest, but the number of cases may be much higher",
            "url": "https://www.newscientist.com/article/2233269-how-bad-is-the-covid-19-coronavirus-outbreak-likely-to-get/",
            "urlToImage": "https://images.newscientist.com/wp-content/uploads/2020/02/11174644/pa-50220781.jpg",
            "publishedAt": "2020-02-11T17:56:02Z",
            "content": "By Debora MacKenzie\r\nSterilisation efforts in Lianyungang, China\r\nTPG/Zuma Press/PA Images\r\nThe World Health Organization has now named the new coronavirus disease: Covid-19.\r\nIf the virus isnt halted, it could infect 60 per cent of the worlds population and \u2026 [+3160 chars]"
        },
        {
            "source": {
                "id": "new-scientist",
                "name": "New Scientist"
            },
            "author": "Michael Le Page",
            "title": "Covid-19: The new coronavirus now officially has a name",
            "description": "The new coronavirus began spreading in China during December 2019, but it has only now been officially named as Covid-19 by the World Health Organization",
            "url": "https://www.newscientist.com/article/2233218-covid-19-the-new-coronavirus-now-officially-has-a-name/",
            "urlToImage": "https://images.newscientist.com/wp-content/uploads/2020/02/11161956/gettyimages-1200005241.jpg",
            "publishedAt": "2020-02-11T16:24:48Z",
            "content": "By Michael Le Page\r\nChinese officials have begun disinfecting to tackle Covid-19\r\n Zhang Peng/LightRocket via Getty Images\r\nThere is now have an official name for the disease caused by the new coronavirus, which has killed more than 1000 people so far: Covid-\u2026 [+1675 chars]"
        },
        {
            "source": {
                "id": "new-scientist",
                "name": "New Scientist"
            },
            "author": "Michael Le Page",
            "title": "Covid-19: The new coronavirus disease now officially has a name",
            "description": "The new coronavirus began spreading in China during December 2019, but the disease it causes has only now been officially named as Covid-19 by the World Health Organization",
            "url": "https://www.newscientist.com/article/2233218-covid-19-the-new-coronavirus-disease-now-officially-has-a-name/",
            "urlToImage": "https://images.newscientist.com/wp-content/uploads/2020/02/11161956/gettyimages-1200005241.jpg",
            "publishedAt": "2020-02-11T16:24:48Z",
            "content": "By Michael Le Page\r\nChinese officials have begun disinfecting to tackle Covid-19\r\n Zhang Peng/LightRocket via Getty Images\r\nThere is now have an official name for the disease caused by the new coronavirus, which has killed more than 1000 people so far: Covid-\u2026 [+1675 chars]"
        },
        {
            "source": {
                "id": "new-scientist",
                "name": "New Scientist"
            },
            "author": "Michael Le Page",
            "title": "Could the new coronavirus really kill 50 million people worldwide?",
            "description": "No one can say for sure how widely the new coronavirus will spread and how many it will kill because there are still many key things we do not know - not least the wider impact on healthcare services",
            "url": "https://www.newscientist.com/article/2233085-could-the-new-coronavirus-really-kill-50-million-people-worldwide/",
            "urlToImage": "https://images.newscientist.com/wp-content/uploads/2020/02/11144246/pa-50222730.jpg",
            "publishedAt": "2020-02-11T14:54:04Z",
            "content": "By Michael Le Page\r\nThere are many things we don\u2019t know about the new coronavirus\r\nLi Jianan/Xinhua News Agency/PA Images\r\nIf the spread of the new coronavirus is not halted, it could infect 60 per cent of the worlds population and kill 1 in 100 of those infe\u2026 [+4561 chars]"
        }
    ]
}